ITR_examples/ITR_DV.py
ITR_examples/ITR_UI.py
ITR_examples/__init__.py
ITR_examples/data/20220215 ITR Tool Sample Data.xlsx
ITR_examples/data/20220720 ITR Tool Sample Data.xlsx
ITR_examples/data/20220720 ITR Tool Test Data.xlsx
ITR_examples/data/20220927 ITR Tool Sample Data.xlsx
ITR_examples/data/20220927 ITR Tool Test Data.xlsx
ITR_examples/data/20220927 ITR V2 Sample Data.xlsx
ITR_examples/data/20221025 ITR V2 Sample Data.xlsx
ITR_examples/data/20230106 ITR V2 Sample Data.xlsx
ITR_examples/data/20230524 ITR V2 SBTi.xlsx
ITR_examples/environment.yml
ITR_examples/utils.py
itr_examples-1.1.9.dist-info/METADATA
itr_examples-1.1.9.dist-info/WHEEL
itr_examples-1.1.9.dist-info/entry_points.txt
itr_examples-1.1.9.dist-info/licenses/LICENSE.txt
itr_examples-1.1.9.dist-info/RECORD
