Metadata-Version: 2.1
Name: ITR-examples
Version: 1.1.9
Summary: Example code and user interface for the ITR project.
Keywords: Climate,ITR,Finance
Author-Email: Michael Tiemann <72577720+MichaelTiemannOSC@users.noreply.github.com>
License: Apache-2.0
Classifier: Intended Audience :: Developers
Classifier: Intended Audience :: Science/Research
Classifier: License :: OSI Approved :: Apache Software License
Classifier: Operating System :: MacOS
Classifier: Operating System :: Microsoft :: Windows
Classifier: Operating System :: Unix
Classifier: Programming Language :: Python
Classifier: Programming Language :: Python :: 3
Classifier: Programming Language :: Python :: 3 :: Only
Classifier: Programming Language :: Python :: 3.12
Classifier: Programming Language :: Python :: 3.11
Classifier: Programming Language :: Python :: 3.10
Classifier: Topic :: Office/Business :: Financial
Classifier: Topic :: Scientific/Engineering
Classifier: Topic :: Software Development
Project-URL: Homepage, https://github.com/os-climate/ITR-examples
Project-URL: Repository, https://github.com/os-climate/ITR-examples
Project-URL: Downloads, https://github.com/os-climate/ITR-examples/releases
Project-URL: Bug Tracker, https://github.com/os-climate/ITR-examples/issues
Project-URL: Documentation, https://github.com/os-climate/ITR-examples/tree/main/docs
Project-URL: Source Code, https://github.com/os-climate/ITR-examples
Requires-Python: <3.13,>=3.10
Requires-Dist: ITR>=1.1.10
Requires-Dist: pip>=23.3.1
Requires-Dist: dash>=2.16.1
Requires-Dist: dash-bootstrap-components>=1.6.0
Requires-Dist: diskcache>=5.6.3
Requires-Dist: flask>=3.0.3
Requires-Dist: jupyterlab>=4.2.5
Requires-Dist: kaleido>=0.2.1
Requires-Dist: matplotlib>=3.8.4
Requires-Dist: multiprocess>=0.70.16
Requires-Dist: plotly>=5.21.0
